xengsort/cptasks_kmers.py
xengsort/dnaencode.py
xengsort/dnaencode_fast.py
xengsort/fastcash_info.py
xengsort/fastcash_main.py
xengsort/fastcash_optimize.py
xengsort/hash_minimizer.py
xengsort/hash_s3c_fbcbvb.py
xengsort/hash_srh_fbcbvb.py
xengsort/kmers.py
xengsort/mask.py
xengsort/mathutils.py
xengsort/parameters.py
xengsort/srhash.py
xengsort/subtable_hashfunctions.py
xengsort/io/binaryio.py
xengsort/io/fastaio.py
xengsort/io/fastqio.py
xengsort/io/generalio.py
xengsort/io/hashio.py
xengsort/io/seqio.py
xengsort/io/textio.py
xengsort/io/xorio.py
xengsort/lowlevel/aligned_arrays.py
xengsort/lowlevel/bitarray.py
xengsort/lowlevel/conpro.py
xengsort/lowlevel/debug.py
xengsort/lowlevel/intbitarray.py
xengsort/lowlevel/libc.py
xengsort/lowlevel/llvm.py
xengsort/lowlevel/numbautils.py
xengsort/lowlevel/packedarray.py
xengsort/values/xenograft.py
xengsort/xengsort/xengsort_classify.py
xengsort/xengsort/xengsort_index.py
xengsort/xengsort/xengsort_info.py
xengsort/xengsort/xengsort_load.py
xengsort/xengsort/xengsort_main.py
xengsort/xengsort/xengsort_remove.py
xengsort/xengsort/xengsort_weak.py
xengsort/xengsort/config/classify.yaml
xengsort/xengsort/config/index.yaml
xengsort-2.1.0.dist-info/licenses/LICENSE
xengsort-2.1.0.dist-info/METADATA
xengsort-2.1.0.dist-info/WHEEL
xengsort-2.1.0.dist-info/entry_points.txt
xengsort-2.1.0.dist-info/top_level.txt
xengsort-2.1.0.dist-info/RECORD
