Metadata-Version: 2.4
Name: xengsort
Version: 2.1.0
Summary: xenograft sorting of FASTQ reads into five categories: host, graft, both, neither, ambiguous.
Author-email: Jens Zentgraf <zentgraf@cs.uni-saarland.de>, Sven Rahmann <rahmann@cs.uni-saarland.de>
License: MIT License
Project-URL: Homepage, https://gitlab.com/genomeinformatics/xengsort
Project-URL: Bug Tracker, https://gitlab.com/genomeinformatics/xengsort/issues
Classifier: Programming Language :: Python :: 3
Classifier: License :: OSI Approved :: MIT License
Classifier: Operating System :: OS Independent
Classifier: Development Status :: 5 - Production/Stable
Classifier: Environment :: Console
Classifier: Intended Audience :: Science/Research
Classifier: Natural Language :: English
Classifier: Topic :: Scientific/Engineering :: Bio-Informatics
Requires-Python: >=3.12
License-File: LICENSE
Requires-Dist: numpy
Requires-Dist: numba
Requires-Dist: pytest
Requires-Dist: jsonargparse>=4.29.0
Requires-Dist: pip
Dynamic: license-file
